MANIFEST.in
README.md
requirements.txt
setup.cfg
setup.py
zabbixctl/Zabbix.py
zabbixctl/__init__.py
zabbixctl/cli.py
zabbixctl/utils.py
zabbixctl.egg-info/PKG-INFO
zabbixctl.egg-info/SOURCES.txt
zabbixctl.egg-info/dependency_links.txt
zabbixctl.egg-info/entry_points.txt
zabbixctl.egg-info/pbr.json
zabbixctl.egg-info/requires.txt
zabbixctl.egg-info/top_level.txt