Metadata-Version: 1.0
Name: zabbixctl
Version: 1.1.4
Summary: zabbixctl - Utility that connects to Zabbix API
Home-page: https://github.com/teriyakichild/zabbixctl
Author: Tony Rogers
Author-email: tony.rogers@rackspace.com
License: ASLv2
Platform: UNKNOWN
